euriai/__init__.py
euriai/autogen.py
euriai/cli.py
euriai/client.py
euriai/crewai.py
euriai/direct.py
euriai/embedding.py
euriai/euri_chat.py
euriai/euri_embed.py
euriai/langchain.py
euriai/langgraph.py
euriai/llamaindex.py
euriai/n8n.py
euriai/smolagents.py
euriai-1.0.31.dist-info/METADATA
euriai-1.0.31.dist-info/WHEEL
euriai-1.0.31.dist-info/entry_points.txt
euriai-1.0.31.dist-info/top_level.txt
euriai-1.0.31.dist-info/RECORD
