Metadata-Version: 2.4
Name: euriai
Version: 1.0.31
Summary: Python client for Euri API (euron.one) with CLI, LangChain, and LlamaIndex integration
Author: Euri
Author-email: tech@euron.one
License: MIT
Keywords: euriai,llm,langchain,llamaindex,langgraph,smolagents,n8n,agents,ai,sdk
Classifier: Programming Language :: Python :: 3
Classifier: Operating System :: OS Independent
Classifier: License :: OSI Approved :: MIT License
Classifier: Intended Audience :: Developers
Requires-Python: >=3.6
Requires-Dist: requests
Requires-Dist: numpy
Requires-Dist: pyyaml
Provides-Extra: langchain-core
Requires-Dist: langchain-core; extra == "langchain-core"
Provides-Extra: langchain
Requires-Dist: langchain; extra == "langchain"
Provides-Extra: llama-index
Requires-Dist: llama-index>=0.10.0; extra == "llama-index"
Provides-Extra: langgraph
Requires-Dist: langgraph; extra == "langgraph"
Provides-Extra: smolagents
Requires-Dist: smolagents; extra == "smolagents"
Provides-Extra: n8n
Requires-Dist: requests; extra == "n8n"
Provides-Extra: crewai
Requires-Dist: crewai; extra == "crewai"
Provides-Extra: autogen
Requires-Dist: pyautogen; extra == "autogen"
Provides-Extra: test
Requires-Dist: pytest; extra == "test"
Provides-Extra: all
Requires-Dist: langchain-core; extra == "all"
Requires-Dist: langchain; extra == "all"
Requires-Dist: llama-index>=0.10.0; extra == "all"
Requires-Dist: langgraph; extra == "all"
Requires-Dist: smolagents; extra == "all"
Requires-Dist: crewai; extra == "all"
Requires-Dist: pyautogen; extra == "all"
Dynamic: author
Dynamic: author-email
Dynamic: classifier
Dynamic: description
Dynamic: description-content-type
Dynamic: license
Dynamic: provides-extra
Dynamic: requires-dist
Dynamic: requires-python
Dynamic: summary
